{
  "kind": "collectionType",
  "collectionName": "blogs",
  "info": {
    "singularName": "blog",
    "pluralName": "blogs",
    "displayName": "blogs"
  },
  "options": {
    "draftAndPublish": true
  },
  "pluginOptions": {},
  "attributes": {
    "Title": {
      "type": "string"
    },
    "Content": {
      "type": "richtext"
    },
    "Slug": {
      "type": "uid",
      "targetField": "Title"
    },
    "PublishedDate": {
      "type": "date"
    },
    "Image": {
      "allowedTypes": [
        "images",
        "files",
        "videos",
        "audios"
      ],
      "type": "media",
      "multiple": false
    }
  }
}
